fuse/__init__.py
fuse/__main__.py
fuse/__version__.py
fuse/args.py
fuse/cli.py
fuse/console.py
fuse/logger.py
fuse/utils/__init__.py
fuse/utils/classes.py
fuse/utils/files.py
fuse/utils/formatters.py
fuse/utils/generator.py
fuse_tool-2.0.1.dist-info/LICENSE
fuse_tool-2.0.1.dist-info/METADATA
fuse_tool-2.0.1.dist-info/WHEEL
fuse_tool-2.0.1.dist-info/entry_points.txt
fuse_tool-2.0.1.dist-info/RECORD
