Metadata-Version: 2.3
Name: fuse-tool
Version: 2.0.1
Summary: Customizable wordlist generator with advanced pattern.
License: MIT
Author: Ryan R.
Author-email: dev.richarlison@proton.me
Requires-Python: >=3.10
Classifier: License :: OSI Approved :: MIT License
Classifier: Programming Language :: Python :: 3
Classifier: Programming Language :: Python :: 3.10
Classifier: Programming Language :: Python :: 3.11
Classifier: Programming Language :: Python :: 3.12
Classifier: Programming Language :: Python :: 3.13
